LICENSE
MANIFEST.in
README.md
setup.py
monscale/__init__.py
monscale/admin.py
monscale/entrypoints.py
monscale/models.py
monscale/rules.py
monscale/tests.py
monscale/urls.py
monscale/views.py
monscale.egg-info/PKG-INFO
monscale.egg-info/SOURCES.txt
monscale.egg-info/dependency_links.txt
monscale.egg-info/entry_points.txt
monscale.egg-info/requires.txt
monscale.egg-info/top_level.txt
monscale/management/__init__.py
monscale/management/commands/__init__.py
monscale/management/commands/action_worker.py
monscale/management/commands/evaluate_context.py
monscale/management/commands/export.py
monscale/management/commands/import.py
monscale/management/commands/trap_worker.py
monscale/mappings/__init__.py
monscale/mappings/actions.py
monscale/mappings/aws.py
monscale/mappings/cloudforms.py
monscale/mappings/metrics.py
monscale/mappings/snmp.py
monscale/migrations/0002_auto__del_field_threshold_active__add_field_monitoredservice_active.py
monscale/migrations/0003_auto__del_field_monitoredservice_username__del_field_monitoredservice_.py
monscale/migrations/__init__.py
monscale/pypelib/Condition.py
monscale/pypelib/Rule.py
monscale/pypelib/RuleTable.py
monscale/pypelib/__init__.py
monscale/pypelib/parsing/ParseEngine.py
monscale/pypelib/parsing/__init__.py
monscale/pypelib/parsing/drivers/RegexParser.py
monscale/pypelib/parsing/drivers/__init__.py
monscale/pypelib/persistence/PersistenceEngine.py
monscale/pypelib/persistence/__init__.py
monscale/pypelib/persistence/backends/__init__.py
monscale/pypelib/persistence/backends/django/Django.py
monscale/pypelib/persistence/backends/django/RuleModel.py
monscale/pypelib/persistence/backends/django/RuleTableModel.py
monscale/pypelib/persistence/backends/django/__init__.py
monscale/pypelib/persistence/backends/rawfile/RAWFile.py
monscale/pypelib/persistence/backends/rawfile/__init__.py
monscale/pypelib/resolver/Resolver.py
monscale/pypelib/resolver/__init__.py
monscale/pypelib/utils/Exceptions.py
monscale/pypelib/utils/Logger.py
monscale/pypelib/utils/__init__.py