Metadata-Version: 1.1
Name: monscale
Version: 0.10
Summary: A Django app that monitor services and acts on them
Home-page: http://blog.digitalhigh.es
Author: Javier Pardo Blasco(jpardobl)
Author-email: jpardo@digitalhigh.es
License: BSD License
Platform: UNKNOWN
Classifier: Environment :: Web Environment
Classifier: Environment :: Console
Classifier: Framework :: Django
Classifier: Intended Audience :: Developers
Classifier: Intended Audience :: System Administrators
Classifier: License :: OSI Approved :: BSD License
Classifier: Operating System :: OS Independent
Classifier: Programming Language :: Python
Classifier: Programming Language :: Python :: 2.6
Classifier: Programming Language :: Python :: 2.7
Classifier: Topic :: System :: Systems Administration
Classifier: Topic :: System :: Monitoring
Classifier: Topic :: Utilities
